efilter/__init__.py
efilter/_version.py
efilter/api.py
efilter/ast.py
efilter/dispatch.py
efilter/errors.py
efilter/protocol.py
efilter/query.py
efilter/scope.py
efilter/syntax.py
efilter/version.py
efilter/ext/__init__.py
efilter/ext/csv_reader.py
efilter/ext/lazy_repetition.py
efilter/ext/line_reader.py
efilter/parsers/__init__.py
efilter/parsers/lisp.py
efilter/parsers/literal.py
efilter/parsers/common/__init__.py
efilter/parsers/common/ast_transforms.py
efilter/parsers/common/grammar.py
efilter/parsers/common/parser.py
efilter/parsers/common/token_stream.py
efilter/parsers/common/tokenizer.py
efilter/parsers/dottysql/__init__.py
efilter/parsers/dottysql/grammar.py
efilter/parsers/dottysql/parser.py
efilter/parsers/legacy/__init__.py
efilter/parsers/legacy/objectfilter.py
efilter/protocols/__init__.py
efilter/protocols/applicative.py
efilter/protocols/associative.py
efilter/protocols/boolean.py
efilter/protocols/counted.py
efilter/protocols/eq.py
efilter/protocols/hashable.py
efilter/protocols/indexable.py
efilter/protocols/iset.py
efilter/protocols/number.py
efilter/protocols/ordered.py
efilter/protocols/reducer.py
efilter/protocols/repeated.py
efilter/protocols/string.py
efilter/protocols/structured.py
efilter/stdlib/__init__.py
efilter/stdlib/core.py
efilter/stdlib/io.py
efilter/stdlib/math.py
efilter/transforms/__init__.py
efilter/transforms/asdottysql.py
efilter/transforms/aslisp.py
efilter/transforms/normalize.py
efilter/transforms/solve.py
rekall_efilter-1.6.0.dist-info/DESCRIPTION.rst
rekall_efilter-1.6.0.dist-info/METADATA
rekall_efilter-1.6.0.dist-info/RECORD
rekall_efilter-1.6.0.dist-info/WHEEL
rekall_efilter-1.6.0.dist-info/metadata.json
rekall_efilter-1.6.0.dist-info/top_level.txt
sample_projects/__init__.py
sample_projects/star_catalog/__init__.py
sample_projects/star_catalog/star_catalog.py
sample_projects/star_catalog/star_catalog_test.py
sample_projects/tagging/__init__.py
sample_projects/tagging/tag.py
sample_projects/tagging/tag_test.py
