Metadata-Version: 2.0
Name: rekall-efilter
Version: 1.6.0
Summary: EFILTER query language
Home-page: https://github.com/google/dotty/
Author: Adam Sindelar and Michael Cohen
Author-email: adam.sindelar@gmail.com and mic@rekall-innovations.com
License: Apache 2.0
Platform: UNKNOWN
Requires-Dist: python-dateutil (>2)
Requires-Dist: future (==0.16.0)
Requires-Dist: pytz (>=2011k)
Requires-Dist: six (>=1.4.0)
